hashid/__init__.py
hashid/cli/__init__.py
hashid/cli/main.py
hashid/core/__init__.py
hashid/core/analyzer.py
hashid_analyzer-2.0.0.dist-info/licenses/LICENSE
hashid_analyzer-2.0.0.dist-info/METADATA
hashid_analyzer-2.0.0.dist-info/WHEEL
hashid_analyzer-2.0.0.dist-info/entry_points.txt
hashid_analyzer-2.0.0.dist-info/top_level.txt
hashid_analyzer-2.0.0.dist-info/RECORD
