Metadata-Version: 2.4
Name: hashid-analyzer
Version: 2.0.0
Summary: Comprehensive hash and token analyzer with persistent mode for security professionals
Home-page: https://github.com/ninxp07/hash-id
Author: XPAlchemnist
Author-email: XPAlchemnist <xpalchemnist@gmail.com>
License: MIT License
Project-URL: Homepage, https://github.com/ninxp07/hash-id
Project-URL: Bug Tracker, https://github.com/ninxp07/hash-id/issues
Project-URL: Source Code, https://github.com/ninxp07/hash-id
Project-URL: Documentation, https://github.com/ninxp07/hash-id#readme
Keywords: hash,analyzer,identification,security,cryptography,md5,sha1,sha256,sha512,ntlm,jwt,token,bcrypt,scrypt,pbkdf2,cryptocurrency,bitcoin,ethereum,penetration-testing,red-team,blue-team,cybersecurity,forensics,malware-analysis
Classifier: Development Status :: 5 - Production/Stable
Classifier: Intended Audience :: Information Technology
Classifier: Intended Audience :: System Administrators
Classifier: Topic :: Security
Classifier: Topic :: Security :: Cryptography
Classifier: Topic :: System :: Systems Administration
Classifier: Topic :: Utilities
Classifier: License :: OSI Approved :: MIT License
Classifier: Programming Language :: Python :: 3
Classifier: Programming Language :: Python :: 3.7
Classifier: Programming Language :: Python :: 3.8
Classifier: Programming Language :: Python :: 3.9
Classifier: Programming Language :: Python :: 3.10
Classifier: Programming Language :: Python :: 3.11
Classifier: Programming Language :: Python :: 3.12
Classifier: Operating System :: OS Independent
Classifier: Environment :: Console
Requires-Python: >=3.7
License-File: LICENSE
Requires-Dist: requests>=2.25.0
Provides-Extra: dev
Requires-Dist: pytest>=6.0; extra == "dev"
Requires-Dist: pytest-cov>=2.0; extra == "dev"
Requires-Dist: black>=21.0; extra == "dev"
Requires-Dist: flake8>=3.8; extra == "dev"
Requires-Dist: mypy>=0.812; extra == "dev"
Provides-Extra: full
Requires-Dist: bcrypt>=3.2.0; extra == "full"
Requires-Dist: PyJWT>=2.0.0; extra == "full"
Dynamic: author
Dynamic: home-page
Dynamic: license-file
Dynamic: requires-python
